nepali_date_utils/__init__.py
nepali_date_utils/date_converter.py
nepali_date_utils/data/__init__.py
nepali_date_utils/data/data.py
tests/__init__.py
tests/test_date_converter.py
nepali_date_utils-0.3.1.dist-info/LICENSE
nepali_date_utils-0.3.1.dist-info/METADATA
nepali_date_utils-0.3.1.dist-info/WHEEL
nepali_date_utils-0.3.1.dist-info/top_level.txt
nepali_date_utils-0.3.1.dist-info/RECORD
