Metadata-Version: 2.1
Name: nepali_date_utils
Version: 0.3.1
Summary: Convert Nepali to English Dates: Easily switch between Nepali and English dates with this Python package.
Home-page: https://github.com/nrjadkry/nepali-date-utils
Author: Niraj Adhikari
Author-email: nrjadkry@gmail.com
License: GPLv3
Keywords: date,nepali-date
Classifier: Development Status :: 3 - Alpha
Classifier: Intended Audience :: Developers
Classifier: Topic :: Scientific/Engineering :: GIS
Classifier: License :: OSI Approved :: GNU Affero General Public License v3
Classifier: Programming Language :: Python :: 3.8
License-File: LICENSE
